Workbook

Sheet Cover

Sheet Historical Financials
A1: Financial Metric | B1: 2022A | C1: 2023A | D1: 2024A | E1: 2025A
A3: Revenue (£m) | B3: 1381.5 | C3: 1633 | D3: 1583.9 | E3: 1257.7
A4: Revenue Growth | C4: =C3/B3-1 -> 0.1820485 | D4: =D3/C3-1 -> -0.030067361 | E4: =E3/D3-1 -> -0.20594735
A5: Cost of Sales | B5: -930.8 | C5: -993.6 | D5: -1000 | E5: -887.9
A6: Gross Profit (£m) | B6: 450.7 | C6: 639 | D6: 583.9 | E6: 369.8
A7: Gross Margin | B7: =B6/B3 -> 0.32623959 | C7: =C6/C3 -> 0.39130435 | D7: =D6/D3 -> 0.36864701 | E7: =E6/E3 -> 0.29402878
A9: Adjusted Operating Expenses | B9: -568.6 | C9: -718.9 | D9: -666.7 | E9: -559
A10: Adjusted EBIT (£m) | B10: -117.9 | C10: -79.7 | D10: -82.8 | E10: -189.2
A11: Adjusted EBIT Margin | B11: =B10/B3 -> -0.08534202 | C11: =C10/C3 -> -0.048805879 | D11: =D10/D3 -> -0.052276028 | E11: =E10/E3 -> -0.15043333
A12: Reported Operating Profit / (Loss) (£m) | B12: -141.8 | C12: -111.2 | D12: -99.5 | E12: -259.2
A14: Loss Before Tax (£m) | B14: -495 | C14: -239.8 | D14: -289.1 | E14: -363.9
A15: Tax | B15: -32.7 | C15: 13 | D15: -34.4 | E15: -129.1
A16: Net Income / (Loss) | B16: -527.7 | C16: -226.8 | D16: -323.5 | E16: -493
A18: Adjusted EBITDA (£m) | B18: 190.2 | C18: 305.9 | D18: 271 | E18: 108.1
A19: Adjusted EBITDA Margin | B19: =B18/B3 -> 0.13767644 | C19: =C18/C3 -> 0.18732394 | D19: =D18/D3 -> 0.17109666 | E19: =E18/E3 -> 0.085950545
A21: Operating Cash Flow (£m) | B21: 127.1 | C21: 145.9 | D21: 123.9 | E21: 74.1
A22: Capital Expenditure | B22: -286.9 | C22: -396.9 | D22: -400.6 | E22: -341
A23: Free Cash Flow (£m) | B23: -298.8 | C23: -360 | D23: -391.6 | E23: -409.9
A25: Cash (£m) | B25: 583.3 | C25: 392.4 | D25: 359.6 | E25: 249.9
A26: Borrowings (£m) | D26: 1387.3 | E26: 1500.2
A27: Net Debt (£m) | B27: 765.5 | C27: 814.3 | D27: 1162.7 | E27: 1380.3
A29: Wholesale Volumes | B29: 6412 | C29: 6620 | D29: 6030 | E29: 5448

Sheet Assumptions
A1: Financial Metric | B1: 2026E | C1: 2027E | D1: 2028E | E1: 2029E | F1: 2030E
A3: Wholesale Volumes | B3: 5450 | C3: 5700 | D3: 5900 | E3: 6050 | F3: 6150
A4: Wholesale Volume Growth | C4: =C3/B3-1 -> 0.04587156 | D4: =D3/C3-1 -> 0.035087719 | E4: =E3/D3-1 -> 0.025423729 | F4: =F3/E3-1 -> 0.016528926
A6: Average Selling Price (£k) | B6: 225 | C6: =B6*(1+C7) -> 236.25 | D6: =C6*(1+D7) -> 245.7 | E6: =D6*(1+E7) -> 254.2995 | F6: =E6*(1+F7) -> 261.92849
A7: ASP Growth | B7: 0.077 | C7: 0.05 | D7: 0.04 | E7: 0.035 | F7: 0.03
A9: Revenue Growth | B9: =((B3*B6)/1000+B18)/'Historical Financials'!E3-1 -> 0.066430786 | C9: =((C3*C6)/1000+C18)/((B3*B6)/1000+B18)-1 -> 0.093476235 | D9: =((D3*D6)/1000+D18)/((C3*C6)/1000+C18)-1 -> 0.073641865 | E9: =((E3*E6)/1000+E18)/((D3*D6)/1000+D18)-1 -> 0.05962161 | F9: =((F3*F6)/1000+F18)/((E3*E6)/1000+E18)-1 -> 0.046357598
A10: Gross Margin | B10: 0.37 | C10: 0.385 | D10: 0.395 | E10: 0.4 | F10: 0.405
A12: Adjusted Operating Expenses (£m) | B12: -535 | C12: -545 | D12: -550 | E12: -555 | F12: -565
A13: Adjusted EBIT Margin | B13: =B10+B12/(((B3*B6)/1000)+B18) -> -0.02888164 | C13: =C10+C12/(((C3*C6)/1000)+C18) -> 0.013398534 | D13: =D10+D12/(((D3*D6)/1000)+D18) -> 0.045711596 | E13: =E10+E12/(((E3*E6)/1000)+E18) -> 0.067368285 | F13: =F10+F12/(((F3*F6)/1000)+F18) -> 0.081377292
A15: D&A (%Revenue) | B15: 0.236 | C15: 0.236 | D15: 0.236 | E15: 0.236 | F15: 0.236
A16: Capital Expenditure (£m) | B16: -340 | C16: -340 | D16: -340 | E16: -340 | F16: -340
A17: Tax Rate | B17: 0.25 | C17: 0.25 | D17: 0.25 | E17: 0.25 | F17: 0.25
A18: Other Revenue (£m) | B18: 115 | C18: 120 | D18: 125 | E18: 130 | F18: 135
A20: Other Operating Cash Adjustments (&Revenue) | B20: 0.685 | C20: 0.685 | D20: 0.685 | E20: 0.685 | F20: 0.685
A21: Interest Rate on Net Debt | B21: 0.105 | C21: 0.105 | D21: 0.105 | E21: 0.105 | F21: 0.105
A22: Working Capital Change (%Revenue) | B22: -0.01 | C22: -0.01 | D22: -0.01 | E22: -0.01 | F22: -0.01

Sheet Income Statement
A1: Financial Metric | B1: 2022A | C1: 2023A | D1: 2024A | E1: 2025A | F1: 2026E | G1: 2027E | H1: 2028E | I1: 2029E | J1: 2030E
A3: Revenue (£m) | B3: ='Historical Financials'!B3 -> 1381.5 | C3: ='Historical Financials'!C3 -> 1633 | D3: ='Historical Financials'!D3 -> 1583.9 | E3: ='Historical Financials'!E3 -> 1257.7 | F3: =E3*(1+Assumptions!B9) -> 1341.25 | G3: =F3*(1+Assumptions!C9) -> 1466.625 | H3: =G3*(1+Assumptions!D9) -> 1574.63 | I3: =H3*(1+Assumptions!E9) -> 1668.512 | J3: =I3*(1+Assumptions!F9) -> 1745.8602
A4: Revenue Growth | C4: =C3/B3-1 -> 0.1820485 | D4: =D3/C3-1 -> -0.030067361 | E4: =E3/D3-1 -> -0.20594735 | F4: =Assumptions!B9 -> 0.066430786 | G4: =Assumptions!C9 -> 0.093476235 | H4: =Assumptions!D9 -> 0.073641865 | I4: =Assumptions!E9 -> 0.05962161 | J4: =Assumptions!F9 -> 0.046357598
A6: Cost of Sales (£m) | B6: ='Historical Financials'!B5 -> -930.8 | C6: ='Historical Financials'!C5 -> -993.6 | D6: ='Historical Financials'!D5 -> -1000 | E6: ='Historical Financials'!E5 -> -887.9 | F6: =F7-F3 -> -844.9875 | G6: =G7-G3 -> -901.97438 | H6: =H7-H3 -> -952.65115 | I6: =I7-I3 -> -1001.1072 | J6: =J7-J3 -> -1038.7868
A7: Gross Profit (£m) | B7: ='Historical Financials'!B6 -> 450.7 | C7: ='Historical Financials'!C6 -> 639 | D7: ='Historical Financials'!D6 -> 583.9 | E7: ='Historical Financials'!E6 -> 369.8 | F7: =F3*F8 -> 496.2625 | G7: =G3*G8 -> 564.65062 | H7: =H3*H8 -> 621.97885 | I7: =I3*I8 -> 667.40479 | J7: =J3*J8 -> 707.07337
A8: Gross Margin | B8: =B7/B3 -> 0.32623959 | C8: =C7/C3 -> 0.39130435 | D8: =D7/D3 -> 0.36864701 | E8: =E7/E3 -> 0.29402878 | F8: =Assumptions!B10 -> 0.37 | G8: =Assumptions!C10 -> 0.385 | H8: =Assumptions!D10 -> 0.395 | I8: =Assumptions!E10 -> 0.4 | J8: =Assumptions!F10 -> 0.405
A10: Adjusted Operating Expenses (£m) | B10: ='Historical Financials'!B9 -> -568.6 | C10: ='Historical Financials'!C9 -> -718.9 | D10: ='Historical Financials'!D9 -> -666.7 | E10: ='Historical Financials'!E9 -> -559 | F10: =Assumptions!B12 -> -535 | G10: =Assumptions!C12 -> -545 | H10: =Assumptions!D12 -> -550 | I10: =Assumptions!E12 -> -555 | J10: =Assumptions!F12 -> -565
A11: D&A (£m) | F11: =F3*Assumptions!B15 -> 316.535 | G11: =G3*Assumptions!C15 -> 346.1235 | H11: =H3*Assumptions!D15 -> 371.61268 | I11: =I3*Assumptions!E15 -> 393.76883 | J11: =J3*Assumptions!F15 -> 412.023
A12: Adjusted EBIT (£m) | B12: ='Historical Financials'!B10 -> -117.9 | C12: ='Historical Financials'!C10 -> -79.7 | D12: ='Historical Financials'!D10 -> -82.8 | E12: ='Historical Financials'!E10 -> -189.2 | F12: =F7+F10 -> -38.7375 | G12: =G7+G10 -> 19.650625 | H12: =H7+H10 -> 71.97885 | I12: =I7+I10 -> 112.40479 | J12: =J7+J10 -> 142.07337
A13: Adjusted EBIT Margin | B13: =B12/B3 -> -0.08534202 | C13: =C12/C3 -> -0.048805879 | D13: =D12/D3 -> -0.052276028 | E13: =E12/E3 -> -0.15043333 | F13: =F12/F3 -> -0.02888164 | G13: =G12/G3 -> 0.013398534 | H13: =H12/H3 -> 0.045711596 | I13: =I12/I3 -> 0.067368285 | J13: =J12/J3 -> 0.081377292
A14: Adjusting Operating Items (£m) | B14: -23.9 | C14: -31.5 | D14: -16.7 | E14: -70 | F14: 0 | G14: 0 | H14: 0 | I14: 0 | J14: 0
A15: Reported Operating Profit / (Loss) (£m) | B15: =B12+B14 -> -141.8 | C15: =C12+C14 -> -111.2 | D15: =D12+D14 -> -99.5 | E15: =E12+E14 -> -259.2 | F15: =F12+F14 -> -38.7375 | G15: =G12+G14 -> 19.650625 | H15: =H12+H14 -> 71.97885 | I15: =I12+I14 -> 112.40479 | J15: =J12+J14 -> 142.07337
A17: Net Financing Expense (£m) | B17: -353.2 | C17: -128.6 | D17: -189.6 | E17: -104.7 | F17: =E17 -> -104.7 | G17: =F17 -> -104.7 | H17: =G17 -> -104.7 | I17: =H17 -> -104.7 | J17: =I17 -> -104.7
A18: Loss Before Tax (£m) | B18: =B15+B17 -> -495 | C18: =C15+C17 -> -239.8 | D18: =D15+D17 -> -289.1 | E18: =E15+E17 -> -363.9 | F18: =F15+F17 -> -143.4375 | G18: =G15+G17 -> -85.049375 | H18: =H15+H17 -> -32.72115 | I18: =I15+I17 -> 7.70479 | J18: =J15+J17 -> 37.373374
A20: Tax (£m) | B20: ='Historical Financials'!B15 -> -32.7 | C20: ='Historical Financials'!C15 -> 13 | D20: ='Historical Financials'!D15 -> -34.4 | E20: ='Historical Financials'!E15 -> -129.1 | F20: =IF(F18>0,-F18*Assumptions!B17,0) -> 0 | G20: =IF(G18>0,-G18*Assumptions!C17,0) -> 0 | H20: =IF(H18>0,-H18*Assumptions!D17,0) -> 0 | I20: =IF(I18>0,-I18*Assumptions!E17,0) -> -1.9261975 | J20: =IF(J18>0,-J18*Assumptions!F17,0) -> -9.3433435
A21: Net Income / (Loss) (£m) | B21: =B18+B20 -> -527.7 | C21: =C18+C20 -> -226.8 | D21: =D18+D20 -> -323.5 | E21: =E18+E20 -> -493 | F21: =F18+F20 -> -143.4375 | G21: =G18+G20 -> -85.049375 | H21: =H18+H20 -> -32.72115 | I21: =I18+I20 -> 5.7785925 | J21: =J18+J20 -> 28.030031
A23: Adjusted EBITDA (£m) | B23: ='Historical Financials'!B18 -> 190.2 | C23: ='Historical Financials'!C18 -> 305.9 | D23: ='Historical Financials'!D18 -> 271 | E23: ='Historical Financials'!E18 -> 108.1 | F23: =F11+F12 -> 277.7975 | G23: =G11+G12 -> 365.77412 | H23: =H11+H12 -> 443.59153 | I23: =I11+I12 -> 506.17362 | J23: =J11+J12 -> 554.09638
A24: Adjusted EBITDA Margin | B24: =B23/B3 -> 0.13767644 | C24: =C23/C3 -> 0.18732394 | D24: =D23/D3 -> 0.17109666 | E24: =E23/E3 -> 0.085950545 | F24: =F23/F3 -> 0.20711836 | G24: =G23/G3 -> 0.24939853 | H24: =H23/H3 -> 0.2817116 | I24: =I23/I3 -> 0.30336828 | J24: =J23/J3 -> 0.31737729

Sheet Cash Flow
A1: Financial Metric | B1: 2022A | C1: 2023A | D1: 2024A | E1: 2025A | F1: 2026E | G1: 2027E | H1: 2028E | I1: 2029E | J1: 2030E
A3: Adjusted EBITDA (£m) | B3: ='Income Statement'!B23 -> 190.2 | C3: ='Income Statement'!C23 -> 305.9 | D3: ='Income Statement'!D23 -> 271 | E3: ='Income Statement'!E23 -> 108.1 | F3: ='Income Statement'!F23 -> 277.7975 | G3: ='Income Statement'!G23 -> 365.77412 | H3: ='Income Statement'!H23 -> 443.59153 | I3: ='Income Statement'!I23 -> 506.17362 | J3: ='Income Statement'!J23 -> 554.09638
A4: Change in Working Capital (£m) | C4: -86 | D4: -118 | E4: 6
A5: Operating Cash Flow (£m) | B5: ='Historical Financials'!B21 -> 127.1 | C5: ='Historical Financials'!C21 -> 145.9 | D5: ='Historical Financials'!D21 -> 123.9 | E5: ='Historical Financials'!E21 -> 74.1 | F5: =F3*Assumptions!B20 -> 190.29129 | G5: =G3*Assumptions!C20 -> 250.55528 | H5: =H3*Assumptions!D20 -> 303.8602 | I5: =I3*Assumptions!E20 -> 346.72893 | J5: =J3*Assumptions!F20 -> 379.55602
A6: Capital Expenditure (£m) | B6: ='Historical Financials'!B22 -> -286.9 | C6: ='Historical Financials'!C22 -> -396.9 | D6: ='Historical Financials'!D22 -> -400.6 | E6: ='Historical Financials'!E22 -> -341 | F6: =Assumptions!B16 -> -340 | G6: =Assumptions!C16 -> -340 | H6: =Assumptions!D16 -> -340 | I6: =Assumptions!E16 -> -340 | J6: =Assumptions!F16 -> -340
A7: Net Cash Interest Paid (£m) | B7: -139 | C7: -109 | D7: -114.9 | E7: -143 | F7: =F17 -> -144.9315 | G7: =G17 -> -175.86872 | H7: =H17 -> -203.72663 | I7: =I17 -> -228.91261 | J7: =J17 -> -252.2419
A8: Free Cash Flow (£m) | B8: =B5+B6+B7 -> -298.8 | C8: =C5+C6+C7 -> -360 | D8: =D5+D6+D7 -> -391.6 | E8: =E5+E6+E7 -> -409.9 | F8: =F5+F6+F7 -> -294.64021 | G8: =G5+G6+G7 -> -265.31345 | H8: =H5+H6+H7 -> -239.86644 | I8: =I5+I6+I7 -> -222.18368 | J8: =J5+J6+J7 -> -212.68588
A11: Opening Net Debt (£m) | F11: ='Historical Financials'!E27 -> 1380.3 | G11: =F14 -> 1674.9402 | H11: =G14 -> 1940.2537 | I11: =H14 -> 2180.1201 | J11: =I14 -> 2402.3038
A12: Free Cash Flow (£m) | F12: =F8 -> -294.64021 | G12: =G8 -> -265.31345 | H12: =H8 -> -239.86644 | I12: =I8 -> -222.18368 | J12: =J8 -> -212.68588
A13: Net Debt Change (£m) | F13: =-F12 -> 294.64021 | G13: =-G12 -> 265.31345 | H13: =-H12 -> 239.86644 | I13: =-I12 -> 222.18368 | J13: =-J12 -> 212.68588
A14: Closing Net Debt (£m) | F14: =F11+F13 -> 1674.9402 | G14: =G11+G13 -> 1940.2537 | H14: =H11+H13 -> 2180.1201 | I14: =I11+I13 -> 2402.3038 | J14: =J11+J13 -> 2614.9897
A15: Average Net Debt (£m) | F15: =(F11+F14)/2 -> 1527.6201 | G15: =(G11+G14)/2 -> 1807.5969 | H15: =(H11+H14)/2 -> 2060.1869 | I15: =(I11+I14)/2 -> 2291.2119 | J15: =(J11+J14)/2 -> 2508.6467
A16: Interest Rate on Net Debt | F16: =Assumptions!B21 -> 0.105 | G16: =Assumptions!C21 -> 0.105 | H16: =Assumptions!D21 -> 0.105 | I16: =Assumptions!E21 -> 0.105 | J16: =Assumptions!F21 -> 0.105
A17: Implied Cash Interest (£m) | F17: =-F11*Assumptions!B21 -> -144.9315 | G17: =-G11*Assumptions!C21 -> -175.86872 | H17: =-H11*Assumptions!D21 -> -203.72663 | I17: =-I11*Assumptions!E21 -> -228.91261 | J17: =-J11*Assumptions!F21 -> -252.2419

Sheet DCF

Sheet Comparable Companies

Sheet Sensitivity Analysis

Sheet Charts
